inverse_canopy/__init__.py
inverse_canopy/__main__.py
inverse_canopy/conditional_events.py
inverse_canopy/early_stop.py
inverse_canopy/end_states.py
inverse_canopy/inverse_canopy.py
inverse_canopy/lognormal_utils.py
inverse_canopy/metrics.py
inverse_canopy/params.py
inverse_canopy/plot.py
inverse_canopy-0.0.22.dist-info/LICENSE
inverse_canopy-0.0.22.dist-info/METADATA
inverse_canopy-0.0.22.dist-info/WHEEL
inverse_canopy-0.0.22.dist-info/top_level.txt
inverse_canopy-0.0.22.dist-info/RECORD
