Metadata-Version: 2.1
Name: inverse-canopy
Version: 0.0.22
Summary: Tensorflow based library for back-fitting event tree conditional/functional event probability distributions to match target end-state frequencies.
Author-email: Arjun Earthperson <a.earthperson@openpra.org>
License: GNU AFFERO GENERAL PUBLIC LICENSE
Project-URL: Homepage, https://openpra.org
Project-URL: Repository, https://github.com/openpra-org/inverse-canopy
Project-URL: Documentation, https://docs.openpra.org
Keywords: tensorflow,probability,event tree,fault tree,scientific
Classifier: Development Status :: 2 - Pre-Alpha
Classifier: Intended Audience :: Developers
Classifier: Intended Audience :: Science/Research
Classifier: License :: OSI Approved :: GNU Affero General Public License v3 or later (AGPLv3+)
Classifier: Operating System :: OS Independent
Classifier: Programming Language :: Python :: 3.10
Classifier: Programming Language :: Python :: 3.11
Classifier: Programming Language :: Python :: 3.12
Classifier: Topic :: Software Development :: Libraries
Classifier: Topic :: Scientific/Engineering
Classifier: Typing :: Typed
Requires-Python: >=3.10
License-File: LICENSE
Requires-Dist: tensorflow>=2.17.0
Requires-Dist: tensorflow-probability>=0.24.0
Requires-Dist: tf-keras>=2.17.0
Requires-Dist: numpy>=1.26.4
Requires-Dist: scipy>=1.14.0
Requires-Dist: matplotlib>=3.9.2
Provides-Extra: cuda
Requires-Dist: tensorflow[and-cuda]; extra == "cuda"
Provides-Extra: metal
Requires-Dist: tensorflow==2.13.1; extra == "metal"
Requires-Dist: tensorflow-metal==1.0.0; extra == "metal"
Requires-Dist: tensorflow-probability==0.21.0; extra == "metal"
Provides-Extra: test
Requires-Dist: pytest-xdist; extra == "test"
Requires-Dist: pytest; extra == "test"
Requires-Dist: pytest-cov; extra == "test"
Requires-Dist: ruff; extra == "test"
Provides-Extra: dev
Requires-Dist: build; extra == "dev"
Requires-Dist: pytest-xdist; extra == "dev"
Requires-Dist: pytest; extra == "dev"
Requires-Dist: pytest-cov; extra == "dev"
Requires-Dist: ruff; extra == "dev"
Requires-Dist: twine; extra == "dev"
